{"nodes": [{"id": "aura_src_components_themeprovider_tsx", "label": "ThemeProvider.tsx", "file_type": "code", "source_file": "aura\\src\\components\\ThemeProvider.tsx", "source_location": "L1"}, {"id": "themeprovider_themeprovider", "label": "ThemeProvider()", "file_type": "code", "source_file": "aura\\src\\components\\ThemeProvider.tsx", "source_location": "L19"}, {"id": "themeprovider_usetheme", "label": "useTheme()", "file_type": "code", "source_file": "aura\\src\\components\\ThemeProvider.tsx", "source_location": "L62"}], "edges": [{"source": "aura_src_components_themeprovider_tsx", "target": "react", "relation": "imports_from", "confidence": "EXTRACTED", "source_file": "aura\\src\\components\\ThemeProvider.tsx", "source_location": "L3", "weight": 1.0}, {"source": "aura_src_components_themeprovider_tsx", "target": "themeprovider_themeprovider", "relation": "contains", "confidence": "EXTRACTED", "source_file": "aura\\src\\components\\ThemeProvider.tsx", "source_location": "L19", "weight": 1.0}, {"source": "aura_src_components_themeprovider_tsx", "target": "themeprovider_usetheme", "relation": "contains", "confidence": "EXTRACTED", "source_file": "aura\\src\\components\\ThemeProvider.tsx", "source_location": "L62", "weight": 1.0}], "raw_calls": [{"caller_nid": "themeprovider_themeprovider", "callee": "useState", "source_file": "aura\\src\\components\\ThemeProvider.tsx", "source_location": "L20"}, {"caller_nid": "themeprovider_themeprovider", "callee": "useState", "source_file": "aura\\src\\components\\ThemeProvider.tsx", "source_location": "L21"}, {"caller_nid": "themeprovider_themeprovider", "callee": "useEffect", "source_file": "aura\\src\\components\\ThemeProvider.tsx", "source_location": "L23"}, {"caller_nid": "themeprovider_themeprovider", "callee": "useEffect", "source_file": "aura\\src\\components\\ThemeProvider.tsx", "source_location": "L28"}, {"caller_nid": "themeprovider_usetheme", "callee": "useContext", "source_file": "aura\\src\\components\\ThemeProvider.tsx", "source_location": "L62"}]}